cothermo_socket/UOMSet.json
cothermo_socket/__init__.py
cothermo_socket/cothermo_socket.py
cothermo_socket/cothermo_socket.py.7317738340c5fc4dd443691b521cd9f4.py
cothermo_socket/uom.py
cothermo_socket/32bit/COThermoSocket.Core.dll
cothermo_socket/64bit/COThermoSocket.Core.dll
cothermo_socket-1.0.0.dist-info/METADATA
cothermo_socket-1.0.0.dist-info/RECORD
cothermo_socket-1.0.0.dist-info/WHEEL
cothermo_socket-1.0.0.dist-info/top_level.txt
